register.v
module register(clk, rst, load, D, Q);
parameter N= 4;
input [N-1: 0] D;
input clk, rst, load;
output reg [N-1: 0] Q;

always @(posedge clk or negedge rst) begin
   if(!rst)
        Q <= {N{1'b0}};
    else if(load)
        Q <= D;
end
endmodule

register_tb.v
`timescale 1ns / 1ps
module register_tb;

reg [3: 0] D;
reg clk, rst, load;
wire [3: 0] Q;

register dut(.clk(clk), .rst(rst), .load(load), .D(D), .Q(Q));

initial clk = 0;
always #5 clk = ~clk;

integer i;
initial begin


    for(i = 0; i < 62; i = i + 1) begin
        {D, rst, load} = i;
        #10;
    end

    #20;
    $finish;
end

initial begin
    $dumpfile("reg.vcd");
    $dumpvars(0, register_tb);

end
endmodule

reg.vcd
$date
	Fri Nov 14 20:53:05 2025
$end
$version
	Icarus Verilog
$end
$timescale
	1ps
$end
$scope module register_tb $end
$var wire 4 ! Q [3:0] $end
$var reg 4 " D [3:0] $end
$var reg 1 # clk $end
$var reg 1 $ load $end
$var reg 1 % rst $end
$var integer 32 & i [31:0] $end
$scope module dut $end
$var wire 4 ' D [3:0] $end
$var wire 1 # clk $end
$var wire 1 $ load $end
$var wire 1 % rst $end
$var parameter 32 ( N $end
$var reg 4 ) Q [3:0] $end
$upscope $end
$upscope $end
$enddefinitions $end
$comment Show the parameter values. $end
$dumpall
b100 (
$end
#0
$dumpvars
b0 )
b0 '
b0 &
0%
0$
0#
b0 "
b0 !
$end
#5000
1#
#10000
0#
1$
b1 &
#15000
1#
#20000
0#
1%
0$
b10 &
#25000
1#
#30000
0#
1$
b11 &
#35000
1#
#40000
0#
b1 "
b1 '
0%
0$
b100 &
#45000
1#
#50000
0#
1$
b101 &
#55000
1#
#60000
0#
1%
0$
b110 &
#65000
1#
#70000
0#
1$
b111 &
#75000
b1 !
b1 )
1#
#80000
b0 !
b0 )
0#
b10 "
b10 '
0%
0$
b1000 &
#85000
1#
#90000
0#
1$
b1001 &
#95000
1#
#100000
0#
1%
0$
b1010 &
#105000
1#
#110000
0#
1$
b1011 &
#115000
b10 !
b10 )
1#
#120000
b0 !
b0 )
0#
b11 "
b11 '
0%
0$
b1100 &
#125000
1#
#130000
0#
1$
b1101 &
#135000
1#
#140000
0#
1%
0$
b1110 &
#145000
1#
#150000
0#
1$
b1111 &
#155000
b11 !
b11 )
1#
#160000
b0 !
b0 )
0#
b100 "
b100 '
0%
0$
b10000 &
#165000
1#
#170000
0#
1$
b10001 &
#175000
1#
#180000
0#
1%
0$
b10010 &
#185000
1#
#190000
0#
1$
b10011 &
#195000
b100 !
b100 )
1#
#200000
b0 !
b0 )
0#
b101 "
b101 '
0%
0$
b10100 &
#205000
1#
#210000
0#
1$
b10101 &
#215000
1#
#220000
0#
1%
0$
b10110 &
#225000
1#
#230000
0#
1$
b10111 &
#235000
b101 !
b101 )
1#
#240000
b0 !
b0 )
0#
b110 "
b110 '
0%
0$
b11000 &
#245000
1#
#250000
0#
1$
b11001 &
#255000
1#
#260000
0#
1%
0$
b11010 &
#265000
1#
#270000
0#
1$
b11011 &
#275000
b110 !
b110 )
1#
#280000
b0 !
b0 )
0#
b111 "
b111 '
0%
0$
b11100 &
#285000
1#
#290000
0#
1$
b11101 &
#295000
1#
#300000
0#
1%
0$
b11110 &
#305000
1#
#310000
0#
1$
b11111 &
#315000
b111 !
b111 )
1#
#320000
b0 !
b0 )
0#
b1000 "
b1000 '
0%
0$
b100000 &
#325000
1#
#330000
0#
1$
b100001 &
#335000
1#
#340000
0#
1%
0$
b100010 &
#345000
1#
#350000
0#
1$
b100011 &
#355000
b1000 !
b1000 )
1#
#360000
b0 !
b0 )
0#
b1001 "
b1001 '
0%
0$
b100100 &
#365000
1#
#370000
0#
1$
b100101 &
#375000
1#
#380000
0#
1%
0$
b100110 &
#385000
1#
#390000
0#
1$
b100111 &
#395000
b1001 !
b1001 )
1#
#400000
b0 !
b0 )
0#
b1010 "
b1010 '
0%
0$
b101000 &
#405000
1#
#410000
0#
1$
b101001 &
#415000
1#
#420000
0#
1%
0$
b101010 &
#425000
1#
#430000
0#
1$
b101011 &
#435000
b1010 !
b1010 )
1#
#440000
b0 !
b0 )
0#
b1011 "
b1011 '
0%
0$
b101100 &
#445000
1#
#450000
0#
1$
b101101 &
#455000
1#
#460000
0#
1%
0$
b101110 &
#465000
1#
#470000
0#
1$
b101111 &
#475000
b1011 !
b1011 )
1#
#480000
b0 !
b0 )
0#
b1100 "
b1100 '
0%
0$
b110000 &
#485000
1#
#490000
0#
1$
b110001 &
#495000
1#
#500000
0#
1%
0$
b110010 &
#505000
1#
#510000
0#
1$
b110011 &
#515000
b1100 !
b1100 )
1#
#520000
b0 !
b0 )
0#
b1101 "
b1101 '
0%
0$
b110100 &
#525000
1#
#530000
0#
1$
b110101 &
#535000
1#
#540000
0#
1%
0$
b110110 &
#545000
1#
#550000
0#
1$
b110111 &
#555000
b1101 !
b1101 )
1#
#560000
b0 !
b0 )
0#
b1110 "
b1110 '
0%
0$
b111000 &
#565000
1#
#570000
0#
1$
b111001 &
#575000
1#
#580000
0#
1%
0$
b111010 &
#585000
1#
#590000
0#
1$
b111011 &
#595000
b1110 !
b1110 )
1#
#600000
b0 !
b0 )
0#
b1111 "
b1111 '
0%
0$
b111100 &
#605000
1#
#610000
0#
1$
b111101 &
#615000
1#
#620000
0#
b111110 &
